django/__init__.py
django/middleware.py
ip_restriction_middleware-1.0.2.dist-info/LICENSE
ip_restriction_middleware-1.0.2.dist-info/METADATA
ip_restriction_middleware-1.0.2.dist-info/WHEEL
ip_restriction_middleware-1.0.2.dist-info/top_level.txt
ip_restriction_middleware-1.0.2.dist-info/RECORD
