Metadata-Version: 2.1
Name: ip-restriction-middleware
Version: 1.0.2
Summary: A middleware for IP-based access restriction in Django
Home-page: https://github.com/Bothrajvasu/IP-Restriction-Middleware
Author: Bothraj P
Author-email: bothrajvasu@gmail.com
Classifier: Programming Language :: Python :: 3
Classifier: License :: OSI Approved :: MIT License
Classifier: Operating System :: OS Independent
Requires-Python: >=3.0
License-File: LICENSE
